pyshake.py
pyshake_constants.py
pyshake_serial_pc.py
pyshake_sk6.py
pyshake_sk6_constants.py
pyshake_sk7.py
pyshake_sk7_constants.py
pyshake_sk_common.py
shake_drivers-1.0.4.dist-info/DESCRIPTION.rst
shake_drivers-1.0.4.dist-info/METADATA
shake_drivers-1.0.4.dist-info/RECORD
shake_drivers-1.0.4.dist-info/WHEEL
shake_drivers-1.0.4.dist-info/metadata.json
shake_drivers-1.0.4.dist-info/top_level.txt
